yunionclient/__init__.py
yunionclient/shell.py
yunionclient/api/__init__.py
yunionclient/api/actionlogs.py
yunionclient/api/baremetalagents.py
yunionclient/api/baremetalnetworks.py
yunionclient/api/baremetals.py
yunionclient/api/baremetalstorages.py
yunionclient/api/buckets.py
yunionclient/api/cachedimages.py
yunionclient/api/client.py
yunionclient/api/cloudaccounts.py
yunionclient/api/cloudproviders.py
yunionclient/api/dbinstances.py
yunionclient/api/disks.py
yunionclient/api/dnsrecords.py
yunionclient/api/dnsrecordsets.py
yunionclient/api/dnszones.py
yunionclient/api/domains.py
yunionclient/api/ec2credentials.py
yunionclient/api/edgewires.py
yunionclient/api/elasticcaches.py
yunionclient/api/endpoints.py
yunionclient/api/filesystems.py
yunionclient/api/flavors.py
yunionclient/api/glanceutils.py
yunionclient/api/groupguests.py
yunionclient/api/groupnetworks.py
yunionclient/api/groups.py
yunionclient/api/groupusers.py
yunionclient/api/guestdisks.py
yunionclient/api/guestnetworks.py
yunionclient/api/guests.py
yunionclient/api/hosts.py
yunionclient/api/hoststorages.py
yunionclient/api/hostwires.py
yunionclient/api/images.py
yunionclient/api/keypairs.py
yunionclient/api/loadbalancers.py
yunionclient/api/logs.py
yunionclient/api/metadatas.py
yunionclient/api/natgateways.py
yunionclient/api/networks.py
yunionclient/api/price_infos.py
yunionclient/api/projects.py
yunionclient/api/quotas.py
yunionclient/api/rates.py
yunionclient/api/reservedips.py
yunionclient/api/roles.py
yunionclient/api/schedtags.py
yunionclient/api/scheduler.py
yunionclient/api/secgroups.py
yunionclient/api/services.py
yunionclient/api/sshrelay.py
yunionclient/api/stats.py
yunionclient/api/storages.py
yunionclient/api/tenantinfo.py
yunionclient/api/tenants.py
yunionclient/api/usages.py
yunionclient/api/users.py
yunionclient/api/vncproxy.py
yunionclient/api/vpcs.py
yunionclient/api/wires.py
yunionclient/api/zones.py
yunionclient/common/__init__.py
yunionclient/common/base.py
python_yunionclient-1.0.20180201.dist-info/LICENSE
python_yunionclient-1.0.20180201.dist-info/METADATA
python_yunionclient-1.0.20180201.dist-info/WHEEL
python_yunionclient-1.0.20180201.dist-info/entry_points.txt
python_yunionclient-1.0.20180201.dist-info/top_level.txt
python_yunionclient-1.0.20180201.dist-info/RECORD
